LICENSE
MANIFEST.in
README.rst
setup.cfg
setup.py
dadaviews/__init__.py
dadaviews/base.py
django_dadaviews.egg-info/PKG-INFO
django_dadaviews.egg-info/SOURCES.txt
django_dadaviews.egg-info/dependency_links.txt
django_dadaviews.egg-info/not-zip-safe
django_dadaviews.egg-info/pbr.json
django_dadaviews.egg-info/top_level.txt