Metadata-Version: 1.1
Name: django-dadaviews
Version: 0.0.3
Summary: A very simple class based views implementation for Django.
Home-page: https://github.com/aino/django-dadaviews
Author: Mikko Hellsing
Author-email: mikko@aino.se
License: ISC
Platform: UNKNOWN
Classifier: Development Status :: 3 - Alpha
Classifier: Environment :: Web Environment
Classifier: Intended Audience :: Developers
Classifier: License :: OSI Approved :: ISC License (ISCL)
Classifier: Operating System :: OS Independent
Classifier: Programming Language :: Python :: 3 :: Only
Classifier: Topic :: Internet :: WWW/HTTP :: Dynamic Content
Classifier: Framework :: Django
